checkout_code/__init__.py
checkout_code-0.5.data/scripts/checkout_code
checkout_code-0.5.dist-info/METADATA
checkout_code-0.5.dist-info/WHEEL
checkout_code-0.5.dist-info/top_level.txt
checkout_code-0.5.dist-info/RECORD
