Metadata-Version: 2.1
Name: checkout-code
Version: 0.5
Summary: Tool to checkout a specific commit to a unique location
Home-page: https://github.com/kanedo/checkout_code
Author: Gabriel Bretschner
Author-email: bretschner@i6.informatik.rwth-aachen.de
License: MIT
Platform: UNKNOWN
Requires-Dist: GitPython
Requires-Dist: filelock
Requires-Dist: python-dotenv
